investimentos/__init__.py
investimentos/investimentos.py
pos_fiap_ml_1-0.2.dist-info/LICENSE
pos_fiap_ml_1-0.2.dist-info/METADATA
pos_fiap_ml_1-0.2.dist-info/WHEEL
pos_fiap_ml_1-0.2.dist-info/top_level.txt
pos_fiap_ml_1-0.2.dist-info/RECORD
