Metadata-Version: 2.1
Name: pos_fiap_ml_1
Version: 0.2
Summary: Uma biblioteca para cálculos de investimentos.
Home-page: https://github.com/Leandro-barreto/fiap_mleng.git
Author: XXXXXX
Author-email: leandro.lhbb@gmail.com
License: MIT
Classifier: Programming Language :: Python :: 3
Classifier: License :: OSI Approved :: MIT License
Classifier: Operating System :: OS Independent
Requires-Python: >=3.6
License-File: LICENSE
